strict_no_cover/__init__.py
strict_no_cover/__main__.py
strict_no_cover-0.1.1.dist-info/licenses/LICENSE
strict_no_cover-0.1.1.dist-info/METADATA
strict_no_cover-0.1.1.dist-info/WHEEL
strict_no_cover-0.1.1.dist-info/entry_points.txt
strict_no_cover-0.1.1.dist-info/top_level.txt
strict_no_cover-0.1.1.dist-info/RECORD
