Metadata-Version: 2.4
Name: strict-no-cover
Version: 0.1.1
Summary: Error on unnecessary `pragma: no cover` comments
Author-email: Samuel Colvin <samuel@pydantic.dev>
License-Expression: MIT
Project-URL: Homepage, https://github.com/samuelcolvin/strict-no-cover
Project-URL: Source, https://github.com/samuelcolvin/strict-no-cover
Classifier: Development Status :: 4 - Beta
Classifier: Programming Language :: Python
Classifier: Programming Language :: Python :: 3
Classifier: Programming Language :: Python :: 3 :: Only
Classifier: Programming Language :: Python :: 3.9
Classifier: Programming Language :: Python :: 3.10
Classifier: Programming Language :: Python :: 3.11
Classifier: Programming Language :: Python :: 3.12
Classifier: Programming Language :: Python :: 3.13
Classifier: Intended Audience :: Developers
Classifier: Intended Audience :: Information Technology
Classifier: Operating System :: OS Independent
Classifier: Topic :: Internet
Classifier: Topic :: Scientific/Engineering :: Artificial Intelligence
Classifier: Topic :: Software Development :: Libraries :: Python Modules
Requires-Python: >=3.9
License-File: LICENSE
Requires-Dist: pydantic>=2.6
Dynamic: license-file
